{"name":"市辖区","statcode":"110100000000"}
{"name":"东城区","statcode":"110101000000"}
{"name":"西城区","statcode":"110102000000"}
{"name":"朝阳区","statcode":"110105000000"}
{"name":"丰台区","statcode":"110106000000"}
{"name":"石景山区","statcode":"110107000000"}
{"name":"海淀区","statcode":"110108000000"}
{"name":"门头沟区","statcode":"110109000000"}
{"name":"房山区","statcode":"110111000000"}
{"name":"通州区","statcode":"110112000000"}
{"name":"顺义区","statcode":"110113000000"}
{"name":"昌平区","statcode":"110114000000"}
{"name":"大兴区","statcode":"110115000000"}
{"name":"怀柔区","statcode":"110116000000"}
{"name":"平谷区","statcode":"110117000000"}
{"name":"密云区","statcode":"110118000000"}
{"name":"延庆区","statcode":"110119000000"}
{"name":"城北街道办事处","statcode":"110114001000"}
{"name":"南口地区办事处","statcode":"110114002000"}
{"name":"马池口地区办事处","statcode":"110114003000"}
{"name":"沙河地区办事处","statcode":"110114004000"}
{"name":"城南街道办事处","statcode":"110114005000"}
{"name":"东小口地区办事处","statcode":"110114007000"}
{"name":"天通苑北街道办事处","statcode":"110114008000"}
{"name":"天通苑南街道办事处","statcode":"110114009000"}
{"name":"霍营街道办事处","statcode":"110114010000"}
{"name":"回龙观街道办事处","statcode":"110114011000"}
{"name":"龙泽园街道办事处","statcode":"110114012000"}
{"name":"史各庄街道办事处","statcode":"110114013000"}
{"name":"阳坊镇","statcode":"110114104000"}
{"name":"小汤山镇","statcode":"110114110000"}
{"name":"南邵镇","statcode":"110114111000"}
{"name":"崔村镇","statcode":"110114112000"}
{"name":"百善镇","statcode":"110114113000"}
{"name":"北七家镇","statcode":"110114115000"}
{"name":"兴寿镇","statcode":"110114116000"}
{"name":"流村镇","statcode":"110114118000"}
{"name":"十三陵镇","statcode":"110114119000"}
{"name":"延寿镇","statcode":"110114120000"}
